Metadata-Version: 2.1
Name: dist-buble
Version: 1.1
Summary: ser&per
Author-email: zykin_gleb@list.ru
